dal/__init__.py
dal/_dal.cpython-39-x86_64-linux-gnu.so
dal/api.py
dal/dal.py
dal/dal_wrap.cpp
dal_python-2024.7.1.dist-info/METADATA
dal_python-2024.7.1.dist-info/WHEEL
dal_python-2024.7.1.dist-info/top_level.txt
dal_python-2024.7.1.dist-info/RECORD
