Metadata-Version: 2.1
Name: dal-python
Version: 2024.7.1
Summary: Python bindings for the DAL library
Author: cheng li
Author-email: wegamekinglc@hotmail.copm
License: BSD 3-Clause
Classifier: Development Status :: 5 - Production/Stable
Classifier: Environment :: Console
Classifier: Intended Audience :: Developers
Classifier: Intended Audience :: Science/Research
Classifier: Intended Audience :: End Users/Desktop
Classifier: License :: OSI Approved :: BSD License
Classifier: Natural Language :: English
Classifier: Programming Language :: C++
Classifier: Programming Language :: Python
Classifier: Topic :: Scientific/Engineering
Classifier: Operating System :: Microsoft :: Windows
Classifier: Operating System :: POSIX
Classifier: Operating System :: Unix
Classifier: Operating System :: MacOS
